jupyter_scheduler/__init__.py
jupyter_scheduler/_version.py
jupyter_scheduler/environments.py
jupyter_scheduler/exceptions.py
jupyter_scheduler/executors.py
jupyter_scheduler/extension.py
jupyter_scheduler/handlers.py
jupyter_scheduler/job_files_manager.py
jupyter_scheduler/models.py
jupyter_scheduler/orm.py
jupyter_scheduler/parameterize.py
jupyter_scheduler/scheduler.py
jupyter_scheduler/task_runner.py
jupyter_scheduler/utils.py
jupyter_scheduler/labextension/build_log.json
jupyter_scheduler/labextension/package.json
jupyter_scheduler/labextension/schemas/@jupyterlab/scheduler/package.json.orig
jupyter_scheduler/labextension/schemas/@jupyterlab/scheduler/plugin.json
jupyter_scheduler/labextension/static/lib_index_js-lib_mainviews_detail-view_job-detail_js-lib_mainviews_list-jobs_js.52c4f7848952fc1901cb.js
jupyter_scheduler/labextension/static/lib_index_js-lib_mainviews_detail-view_job-detail_js-lib_mainviews_list-jobs_js.52c4f7848952fc1901cb.js.map
jupyter_scheduler/labextension/static/node_modules_babel_runtime_helpers_esm_extends_js-_5f2f0.838f72d95f4730bc8273.js
jupyter_scheduler/labextension/static/node_modules_babel_runtime_helpers_esm_extends_js-_5f2f0.838f72d95f4730bc8273.js.map
jupyter_scheduler/labextension/static/node_modules_babel_runtime_helpers_esm_extends_js-_5f2f1.128b43e1b7609ace6dad.js
jupyter_scheduler/labextension/static/node_modules_babel_runtime_helpers_esm_extends_js-_5f2f1.128b43e1b7609ace6dad.js.map
jupyter_scheduler/labextension/static/remoteEntry.dd02c13a40cbdd3ecca0.js
jupyter_scheduler/labextension/static/remoteEntry.dd02c13a40cbdd3ecca0.js.map
jupyter_scheduler/labextension/static/style.js
jupyter_scheduler/labextension/static/style_index_js.c577c4358b4db9c572c8.js
jupyter_scheduler/labextension/static/style_index_js.c577c4358b4db9c572c8.js.map
jupyter_scheduler/labextension/static/vendors-node_modules_cronstrue_dist_cronstrue_js.37b8b19572aa0527c98c.js
jupyter_scheduler_keepalive-2.10.0.post4.dist-info/METADATA
jupyter_scheduler_keepalive-2.10.0.post4.dist-info/WHEEL
jupyter_scheduler_keepalive-2.10.0.post4.dist-info/licenses/LICENSE
jupyter_scheduler_keepalive-2.10.0.post4.dist-info/RECORD
