Metadata-Version: 2.4
Name: jupyter-scheduler-keepalive
Version: 2.10.0.post4
Summary: A JupyterLab extension for running notebook jobs
Project-URL: Homepage, https://github.com/jupyter-server/jupyter-scheduler
Author: Project Jupyter
License: BSD 3-Clause License
License-File: LICENSE
Keywords: Jupyter,JupyterLab,JupyterLab4
Classifier: Framework :: Jupyter
Classifier: Framework :: Jupyter :: JupyterLab
Classifier: Framework :: Jupyter :: JupyterLab :: 4
Classifier: Framework :: Jupyter :: JupyterLab :: Extensions
Classifier: Framework :: Jupyter :: JupyterLab :: Extensions :: Prebuilt
Classifier: License :: OSI Approved :: BSD License
Classifier: Programming Language :: Python
Classifier: Programming Language :: Python :: 3
Classifier: Programming Language :: Python :: 3.9
Classifier: Programming Language :: Python :: 3.10
Classifier: Programming Language :: Python :: 3.11
Classifier: Programming Language :: Python :: 3.12
Classifier: Programming Language :: Python :: 3.13
Requires-Python: >=3.9
Requires-Dist: croniter~=1.4
Requires-Dist: fsspec<=2024.10.0,>=2023.6.0
Requires-Dist: jupyter-server<3,>=1.6
Requires-Dist: nbconvert~=7.0
Requires-Dist: psutil~=5.9
Requires-Dist: pydantic<3,>=1.10
Requires-Dist: pytz<=2024.2,>=2023.3
Requires-Dist: sqlalchemy<3,>=2.0
Requires-Dist: traitlets~=5.0
Provides-Extra: dev
Requires-Dist: click; extra == 'dev'
Provides-Extra: docs
Requires-Dist: myst-parser; extra == 'docs'
Requires-Dist: pydata-sphinx-theme; extra == 'docs'
Requires-Dist: sphinx; extra == 'docs'
Provides-Extra: test
Requires-Dist: jupyter-server[test]<3,>=1.6; extra == 'test'
Requires-Dist: pytest; extra == 'test'
Requires-Dist: pytest-cov; extra == 'test'
